poche/__init__.py
poche/caches.py
poche/items.py
poche/py.typed
poche-1.0.0.dist-info/LICENSE
poche-1.0.0.dist-info/WHEEL
poche-1.0.0.dist-info/METADATA
poche-1.0.0.dist-info/RECORD
