Metadata-Version: 2.1
Name: poche
Version: 1.0.0
Summary: Simple and fast Python in-memory caching library
Home-page: https://github.com/etienne-napoleone/poche
License: GPL-3.0+
Keywords: cache,in-memory,simple,fast,ttl
Author: etienne-napoleone
Author-email: etienne.napoleone@gmail.com
Requires-Python: >=3.6,<4.0
Classifier: Development Status :: 5 - Production/Stable
Classifier: License :: OSI Approved :: GNU General Public License v3 or later (GPLv3+)
Classifier: Programming Language :: Python :: 3
Classifier: Programming Language :: Python :: 3.6
Classifier: Programming Language :: Python :: 3.7
Classifier: Programming Language :: Python :: 3.8
Classifier: Programming Language :: Python :: 3.9
Classifier: Topic :: Database
Classifier: Topic :: Software Development :: Libraries :: Python Modules
Classifier: Topic :: Utilities
Classifier: Typing :: Typed
Project-URL: Repository, https://github.com/etienne-napoleone/poche
